us_labor/__init__.py
us_labor/us_labor.py
us_labor-0.0.1.dist-info/LICENSE
us_labor-0.0.1.dist-info/METADATA
us_labor-0.0.1.dist-info/WHEEL
us_labor-0.0.1.dist-info/top_level.txt
us_labor-0.0.1.dist-info/RECORD
