Metadata-Version: 2.2
Name: us-labor
Version: 0.0.1
Summary: A simple python wrapper for interacting with the US Bureau of Labor Statistics API
Author-email: Nikhil Sunder <nsunder724@gmail.com>
Maintainer-email: Nikhil Sunder <nsunder724@gmail.com>
License:                     GNU GENERAL PUBLIC LICENSE
Project-URL: Repository, https://github.com/nikhilxsunder/fedfred
Project-URL: Issues, https://github.com/nikhilxsunder/fedfred/issues
Project-URL: Documentation, https://fred.stlouisfed.org/docs/api/fred/
Keywords: usbl,bureau of labor,api,economics,labor
Classifier: Programming Language :: Python :: 3
Classifier: License :: OSI Approved :: GNU Affero General Public License v3
Classifier: Operating System :: OS Independent
Classifier: Development Status :: 4 - Beta
Classifier: Intended Audience :: Financial and Insurance Industry
Classifier: Topic :: Office/Business :: Financial :: Investment
Requires-Python: >=3.8
License-File: LICENSE
Requires-Dist: requests
